<?xml version="1.0" encoding="UTF-8"?>
<metadata xml:lang="en"><Esri><CreaDate>20241105</CreaDate><CreaTime>16425900</CreaTime><ArcGISFormat>1.0</ArcGISFormat><SyncOnce>TRUE</SyncOnce><ModDate>20241105</ModDate><ModTime>183211</ModTime></Esri><toolbox name="BufferAnalysis" alias="buffer_toolbox"><arcToolboxHelpPath>c:\users\games\appdata\local\programs\arcgis\pro\Resources\Help\gp</arcToolboxHelpPath><toolsets/></toolbox><dataIdInfo><idCitation><resTitle>BufferAnalysis</resTitle></idCitation></dataIdInfo><distInfo><distributor><distorFormat><formatName>ArcToolbox Toolbox</formatName></distorFormat></distributor></distInfo></metadata>
